cybears/__init__.py
cybears/servers/__init__.py
cybears/servers/filteredhttp.py
cybears/utils/__init__.py
cybears/utils/libc.py
cybears/utils/misc.py
cybears/web/__init__.py
cybears/web/shell.py
cybears-0.2.0.dist-info/METADATA
cybears-0.2.0.dist-info/WHEEL
cybears-0.2.0.dist-info/top_level.txt
cybears-0.2.0.dist-info/RECORD
