Metadata-Version: 2.1
Name: cybears
Version: 0.2.0
Summary: cybears CTF tools and things
Home-page: https://gitlab.com/cybears
Author: @cybearsCTF
License: BSD 2-clause
Platform: UNKNOWN
Classifier: Development Status :: 1 - Planning
Classifier: Intended Audience :: Developers
Classifier: License :: OSI Approved :: BSD License
Classifier: Topic :: Security
Requires-Dist: requests (>=2.24.0)
